machinelearnlib/__init__.py
machinelearnlib/activationFunc.py
machinelearnlib/buildModel.py
machinelearnlib/defineModel.py
machinelearnlib/featureScaling.py
machinelearnlib/initializeWeights.py
machinelearnlib/loadData.py
machinelearnlib/loadModel.py
machinelearnlib/machinelearnlib.py
machinelearnlib/plots.py
machinelearnlib/processList.py
machinelearnlib/testing.py
machinelearnlib/train.py
machinelearnlib/models/__init__.py
machinelearnlib/models/linearRegression.py
machinelearnlib/models/logisticRegression.py
machinelearnlib/models/neuralNet.py
machinelearnlib-0.2.5.dist-info/METADATA
machinelearnlib-0.2.5.dist-info/RECORD
machinelearnlib-0.2.5.dist-info/WHEEL
machinelearnlib-0.2.5.dist-info/top_level.txt
