Metadata-Version: 2.1
Name: machinelearnlib
Version: 0.2.5
Summary: Implementation of common machine learning algorithms
Home-page: https://github.com/Kai-Bailey/machinelearnlib
Author: Kai Bailey
Author-email: kbailey1@ualberta.ca
License: MIT
Keywords: machine learning data science
Platform: UNKNOWN
Requires-Dist: numpy
Requires-Dist: matplotlib
